{
    "DecisionTree": {
        "filter_sizes": [
            12000,
            8000,
            6000,
            4500,
            3500,
            1500,
            1000,
            300
        ],
        "training_time_seconds": [
            38.38599944114685,
            37.49788427352905,
            39.7434139251709,
            41.45486569404602,
            42.529414653778076,
            50.752222299575806,
            46.01419687271118,
            45.586944818496704
        ],
        "num_classes": [
            4,
            4,
            6,
            6,
            6,
            8,
            8,
            9
        ],
        "test_f1_macro": [
            0.41330013535507065,
            0.41330013535507065,
            0.3092501141430602,
            0.3092501141430602,
            0.3092501141430602,
            0.254359136217379,
            0.254359136217379,
            0.243953599492373
        ],
        "test_f1_micro": [
            0.5270864216795402,
            0.5270864216795402,
            0.4767720248603419,
            0.4767720248603419,
            0.4767720248603419,
            0.4585821864450792,
            0.4585821864450792,
            0.4577657317935423
        ],
        "test_f1_weighted": [
            0.5305397291482365,
            0.5305397291482365,
            0.4784881736253,
            0.4784881736253,
            0.4784881736253,
            0.4608474617442954,
            0.4608474617442954,
            0.46019094690487394
        ],
        "cv_class_weights": [
            0.8173960609801901,
            0.8173960609801901,
            1.0858271066334115,
            1.0858271066334115,
            1.0858271066334115,
            1.3307505951129175,
            1.3307505951129175,
            1.4512154713728063
        ],
        "imbalance_ratio": [
            5.861513944223107,
            5.861513944223107,
            16.548314606741574,
            16.548314606741574,
            16.548314606741574,
            56.32823259372609,
            56.32823259372609,
            337.7201834862385
        ],
        "total_training_samples": [
            123041,
            123041,
            132321,
            132321,
            132321,
            135555,
            135555,
            135776
        ],
        "entropy": [
            0.7897965464636147,
            0.7897965464636147,
            0.7367764591776876,
            0.7367764591776876,
            0.7367764591776876,
            0.6821026203869703,
            0.6821026203869703,
            0.649862088035378
        ],
        "test_precision_macro": [
            0.4115917159056786,
            0.4115917159056786,
            0.3086136561756431,
            0.3086136561756431,
            0.3086136561756431,
            0.25323062271155383,
            0.25323062271155383,
            0.24069912044484218
        ],
        "test_recall_macro": [
            0.4154032328292619,
            0.4154032328292619,
            0.31000417992969515,
            0.31000417992969515,
            0.31000417992969515,
            0.2555707721090283,
            0.2555707721090283,
            0.24773901605455156
        ],
        "classification_reports": [
            {
                "0": {
                    "precision": 0.4213106295149639,
                    "recall": 0.4214193548387097,
                    "f1-score": 0.42136498516320475,
                    "support": 3875.0
                },
                "1": {
                    "precision": 0.6754099825729478,
                    "recall": 0.6551798872995231,
                    "f1-score": 0.6651411472199609,
                    "support": 23070.0
                },
                "2": {
                    "precision": 0.23007803263182786,
                    "recall": 0.2519419989642672,
                    "f1-score": 0.24051415152638733,
                    "support": 3862.0
                },
                "3": {
                    "precision": 0.31956821890297477,
                    "recall": 0.33307169021454736,
                    "f1-score": 0.3261802575107296,
                    "support": 7644.0
                },
                "accuracy": 0.5270864216795402,
                "macro avg": {
                    "precision": 0.4115917159056786,
                    "recall": 0.4154032328292619,
                    "f1-score": 0.41330013535507065,
                    "support": 38451.0
                },
                "weighted avg": {
                    "precision": 0.5343327303489337,
                    "recall": 0.5270864216795402,
                    "f1-score": 0.5305397291482365,
                    "support": 38451.0
                }
            },
            {
                "0": {
                    "precision": 0.4213106295149639,
                    "recall": 0.4214193548387097,
                    "f1-score": 0.42136498516320475,
                    "support": 3875.0
                },
                "1": {
                    "precision": 0.6754099825729478,
                    "recall": 0.6551798872995231,
                    "f1-score": 0.6651411472199609,
                    "support": 23070.0
                },
                "2": {
                    "precision": 0.23007803263182786,
                    "recall": 0.2519419989642672,
                    "f1-score": 0.24051415152638733,
                    "support": 3862.0
                },
                "3": {
                    "precision": 0.31956821890297477,
                    "recall": 0.33307169021454736,
                    "f1-score": 0.3261802575107296,
                    "support": 7644.0
                },
                "accuracy": 0.5270864216795402,
                "macro avg": {
                    "precision": 0.4115917159056786,
                    "recall": 0.4154032328292619,
                    "f1-score": 0.41330013535507065,
                    "support": 38451.0
                },
                "weighted avg": {
                    "precision": 0.5343327303489337,
                    "recall": 0.5270864216795402,
                    "f1-score": 0.5305397291482365,
                    "support": 38451.0
                }
            },
            {
                "0": {
                    "precision": 0.3959575019435087,
                    "recall": 0.3879157146483879,
                    "f1-score": 0.3918953577840472,
                    "support": 3939.0
                },
                "1": {
                    "precision": 0.6366525423728814,
                    "recall": 0.6278674966264746,
                    "f1-score": 0.6322295031668457,
                    "support": 22973.0
                },
                "2": {
                    "precision": 0.22839951865222624,
                    "recall": 0.24258691206543967,
                    "f1-score": 0.2352795339035577,
                    "support": 3912.0
                },
                "3": {
                    "precision": 0.1709039548022599,
                    "recall": 0.1754894851341552,
                    "f1-score": 0.17316636851520573,
                    "support": 1379.0
                },
                "4": {
                    "precision": 0.10844155844155844,
                    "recall": 0.11215580926796508,
                    "f1-score": 0.11026741498844503,
                    "support": 1489.0
                },
                "5": {
                    "precision": 0.31132686084142397,
                    "recall": 0.3140096618357488,
                    "f1-score": 0.31266250650026,
                    "support": 7659.0
                },
                "accuracy": 0.4767720248603419,
                "macro avg": {
                    "precision": 0.3086136561756431,
                    "recall": 0.31000417992969515,
                    "f1-score": 0.3092501141430602,
                    "support": 41351.0
                },
                "weighted avg": {
                    "precision": 0.48029292724314915,
                    "recall": 0.4767720248603419,
                    "f1-score": 0.4784881736253,
                    "support": 41351.0
                }
            },
            {
                "0": {
                    "precision": 0.3959575019435087,
                    "recall": 0.3879157146483879,
                    "f1-score": 0.3918953577840472,
                    "support": 3939.0
                },
                "1": {
                    "precision": 0.6366525423728814,
                    "recall": 0.6278674966264746,
                    "f1-score": 0.6322295031668457,
                    "support": 22973.0
                },
                "2": {
                    "precision": 0.22839951865222624,
                    "recall": 0.24258691206543967,
                    "f1-score": 0.2352795339035577,
                    "support": 3912.0
                },
                "3": {
                    "precision": 0.1709039548022599,
                    "recall": 0.1754894851341552,
                    "f1-score": 0.17316636851520573,
                    "support": 1379.0
                },
                "4": {
                    "precision": 0.10844155844155844,
                    "recall": 0.11215580926796508,
                    "f1-score": 0.11026741498844503,
                    "support": 1489.0
                },
                "5": {
                    "precision": 0.31132686084142397,
                    "recall": 0.3140096618357488,
                    "f1-score": 0.31266250650026,
                    "support": 7659.0
                },
                "accuracy": 0.4767720248603419,
                "macro avg": {
                    "precision": 0.3086136561756431,
                    "recall": 0.31000417992969515,
                    "f1-score": 0.3092501141430602,
                    "support": 41351.0
                },
                "weighted avg": {
                    "precision": 0.48029292724314915,
                    "recall": 0.4767720248603419,
                    "f1-score": 0.4784881736253,
                    "support": 41351.0
                }
            },
            {
                "0": {
                    "precision": 0.3959575019435087,
                    "recall": 0.3879157146483879,
                    "f1-score": 0.3918953577840472,
                    "support": 3939.0
                },
                "1": {
                    "precision": 0.6366525423728814,
                    "recall": 0.6278674966264746,
                    "f1-score": 0.6322295031668457,
                    "support": 22973.0
                },
                "2": {
                    "precision": 0.22839951865222624,
                    "recall": 0.24258691206543967,
                    "f1-score": 0.2352795339035577,
                    "support": 3912.0
                },
                "3": {
                    "precision": 0.1709039548022599,
                    "recall": 0.1754894851341552,
                    "f1-score": 0.17316636851520573,
                    "support": 1379.0
                },
                "4": {
                    "precision": 0.10844155844155844,
                    "recall": 0.11215580926796508,
                    "f1-score": 0.11026741498844503,
                    "support": 1489.0
                },
                "5": {
                    "precision": 0.31132686084142397,
                    "recall": 0.3140096618357488,
                    "f1-score": 0.31266250650026,
                    "support": 7659.0
                },
                "accuracy": 0.4767720248603419,
                "macro avg": {
                    "precision": 0.3086136561756431,
                    "recall": 0.31000417992969515,
                    "f1-score": 0.3092501141430602,
                    "support": 41351.0
                },
                "weighted avg": {
                    "precision": 0.48029292724314915,
                    "recall": 0.4767720248603419,
                    "f1-score": 0.4784881736253,
                    "support": 41351.0
                }
            },
            {
                "0": {
                    "precision": 0.3818877551020408,
                    "recall": 0.3855266546484677,
                    "f1-score": 0.38369857747020375,
                    "support": 3883.0
                },
                "1": {
                    "precision": 0.10526315789473684,
                    "recall": 0.10725552050473186,
                    "f1-score": 0.10625,
                    "support": 634.0
                },
                "2": {
                    "precision": 0.6293628562536125,
                    "recall": 0.6155418333623239,
                    "f1-score": 0.6223756238046035,
                    "support": 22996.0
                },
                "3": {
                    "precision": 0.2152622421078797,
                    "recall": 0.22610966057441254,
                    "f1-score": 0.22055265503629187,
                    "support": 3830.0
                },
                "4": {
                    "precision": 0.16712328767123288,
                    "recall": 0.16944444444444445,
                    "f1-score": 0.16827586206896553,
                    "support": 1440.0
                },
                "5": {
                    "precision": 0.10837438423645321,
                    "recall": 0.11055276381909548,
                    "f1-score": 0.10945273631840796,
                    "support": 398.0
                },
                "6": {
                    "precision": 0.11576971214017522,
                    "recall": 0.12052117263843648,
                    "f1-score": 0.11809766996488988,
                    "support": 1535.0
                },
                "7": {
                    "precision": 0.3028015862862991,
                    "recall": 0.3096141268803139,
                    "f1-score": 0.3061699650756694,
                    "support": 7645.0
                },
                "accuracy": 0.4585821864450792,
                "macro avg": {
                    "precision": 0.25323062271155383,
                    "recall": 0.2555707721090283,
                    "f1-score": 0.254359136217379,
                    "support": 42361.0
                },
                "weighted avg": {
                    "precision": 0.4632398857277767,
                    "recall": 0.4585821864450792,
                    "f1-score": 0.4608474617442954,
                    "support": 42361.0
                }
            },
            {
                "0": {
                    "precision": 0.3818877551020408,
                    "recall": 0.3855266546484677,
                    "f1-score": 0.38369857747020375,
                    "support": 3883.0
                },
                "1": {
                    "precision": 0.10526315789473684,
                    "recall": 0.10725552050473186,
                    "f1-score": 0.10625,
                    "support": 634.0
                },
                "2": {
                    "precision": 0.6293628562536125,
                    "recall": 0.6155418333623239,
                    "f1-score": 0.6223756238046035,
                    "support": 22996.0
                },
                "3": {
                    "precision": 0.2152622421078797,
                    "recall": 0.22610966057441254,
                    "f1-score": 0.22055265503629187,
                    "support": 3830.0
                },
                "4": {
                    "precision": 0.16712328767123288,
                    "recall": 0.16944444444444445,
                    "f1-score": 0.16827586206896553,
                    "support": 1440.0
                },
                "5": {
                    "precision": 0.10837438423645321,
                    "recall": 0.11055276381909548,
                    "f1-score": 0.10945273631840796,
                    "support": 398.0
                },
                "6": {
                    "precision": 0.11576971214017522,
                    "recall": 0.12052117263843648,
                    "f1-score": 0.11809766996488988,
                    "support": 1535.0
                },
                "7": {
                    "precision": 0.3028015862862991,
                    "recall": 0.3096141268803139,
                    "f1-score": 0.3061699650756694,
                    "support": 7645.0
                },
                "accuracy": 0.4585821864450792,
                "macro avg": {
                    "precision": 0.25323062271155383,
                    "recall": 0.2555707721090283,
                    "f1-score": 0.254359136217379,
                    "support": 42361.0
                },
                "weighted avg": {
                    "precision": 0.4632398857277767,
                    "recall": 0.4585821864450792,
                    "f1-score": 0.4608474617442954,
                    "support": 42361.0
                }
            },
            {
                "0": {
                    "precision": 0.38839750260145683,
                    "recall": 0.39310163243812535,
                    "f1-score": 0.39073540957864433,
                    "support": 3798.0
                },
                "1": {
                    "precision": 0.0984375,
                    "recall": 0.11413043478260869,
                    "f1-score": 0.10570469798657718,
                    "support": 552.0
                },
                "2": {
                    "precision": 0.6264492914575097,
                    "recall": 0.6132904235887623,
                    "f1-score": 0.6198000219756071,
                    "support": 22994.0
                },
                "3": {
                    "precision": 0.2271746944644141,
                    "recall": 0.2390920554854981,
                    "f1-score": 0.23298107643155566,
                    "support": 3965.0
                },
                "4": {
                    "precision": 0.15444287729196052,
                    "recall": 0.15124309392265192,
                    "f1-score": 0.15282623866015352,
                    "support": 1448.0
                },
                "5": {
                    "precision": 0.15294117647058825,
                    "recall": 0.1780821917808219,
                    "f1-score": 0.16455696202531644,
                    "support": 73.0
                },
                "6": {
                    "precision": 0.11187214611872145,
                    "recall": 0.12760416666666666,
                    "f1-score": 0.1192214111922141,
                    "support": 384.0
                },
                "7": {
                    "precision": 0.09905362776025237,
                    "recall": 0.10494652406417113,
                    "f1-score": 0.10191496267445635,
                    "support": 1496.0
                },
                "8": {
                    "precision": 0.30752326783867634,
                    "recall": 0.30816062176165804,
                    "f1-score": 0.3078416149068323,
                    "support": 7720.0
                },
                "accuracy": 0.4577657317935423,
                "macro avg": {
                    "precision": 0.24069912044484218,
                    "recall": 0.24773901605455156,
                    "f1-score": 0.243953599492373,
                    "support": 42430.0
                },
                "weighted avg": {
                    "precision": 0.46275782788970854,
                    "recall": 0.4577657317935423,
                    "f1-score": 0.46019094690487394,
                    "support": 42430.0
                }
            }
        ],
        "confusion_matrices": [
            [
                [
                    1633,
                    1447,
                    195,
                    600
                ],
                [
                    1538,
                    15115,
                    2283,
                    4134
                ],
                [
                    148,
                    2054,
                    973,
                    687
                ],
                [
                    557,
                    3763,
                    778,
                    2546
                ]
            ],
            [
                [
                    1633,
                    1447,
                    195,
                    600
                ],
                [
                    1538,
                    15115,
                    2283,
                    4134
                ],
                [
                    148,
                    2054,
                    973,
                    687
                ],
                [
                    557,
                    3763,
                    778,
                    2546
                ]
            ],
            [
                [
                    1528,
                    1359,
                    171,
                    121,
                    202,
                    558
                ],
                [
                    1380,
                    14424,
                    2099,
                    647,
                    739,
                    3684
                ],
                [
                    148,
                    1969,
                    949,
                    116,
                    125,
                    605
                ],
                [
                    115,
                    608,
                    143,
                    242,
                    52,
                    219
                ],
                [
                    174,
                    684,
                    143,
                    67,
                    167,
                    254
                ],
                [
                    514,
                    3612,
                    650,
                    223,
                    255,
                    2405
                ]
            ],
            [
                [
                    1528,
                    1359,
                    171,
                    121,
                    202,
                    558
                ],
                [
                    1380,
                    14424,
                    2099,
                    647,
                    739,
                    3684
                ],
                [
                    148,
                    1969,
                    949,
                    116,
                    125,
                    605
                ],
                [
                    115,
                    608,
                    143,
                    242,
                    52,
                    219
                ],
                [
                    174,
                    684,
                    143,
                    67,
                    167,
                    254
                ],
                [
                    514,
                    3612,
                    650,
                    223,
                    255,
                    2405
                ]
            ],
            [
                [
                    1528,
                    1359,
                    171,
                    121,
                    202,
                    558
                ],
                [
                    1380,
                    14424,
                    2099,
                    647,
                    739,
                    3684
                ],
                [
                    148,
                    1969,
                    949,
                    116,
                    125,
                    605
                ],
                [
                    115,
                    608,
                    143,
                    242,
                    52,
                    219
                ],
                [
                    174,
                    684,
                    143,
                    67,
                    167,
                    254
                ],
                [
                    514,
                    3612,
                    650,
                    223,
                    255,
                    2405
                ]
            ],
            [
                [
                    1497,
                    59,
                    1277,
                    158,
                    129,
                    30,
                    181,
                    552
                ],
                [
                    67,
                    68,
                    301,
                    48,
                    19,
                    5,
                    28,
                    98
                ],
                [
                    1401,
                    315,
                    14155,
                    2007,
                    618,
                    188,
                    737,
                    3575
                ],
                [
                    118,
                    63,
                    1829,
                    866,
                    119,
                    44,
                    131,
                    660
                ],
                [
                    149,
                    19,
                    590,
                    144,
                    244,
                    17,
                    43,
                    234
                ],
                [
                    34,
                    7,
                    173,
                    38,
                    22,
                    44,
                    19,
                    61
                ],
                [
                    147,
                    10,
                    694,
                    141,
                    72,
                    16,
                    185,
                    270
                ],
                [
                    507,
                    105,
                    3472,
                    621,
                    237,
                    62,
                    274,
                    2367
                ]
            ],
            [
                [
                    1497,
                    59,
                    1277,
                    158,
                    129,
                    30,
                    181,
                    552
                ],
                [
                    67,
                    68,
                    301,
                    48,
                    19,
                    5,
                    28,
                    98
                ],
                [
                    1401,
                    315,
                    14155,
                    2007,
                    618,
                    188,
                    737,
                    3575
                ],
                [
                    118,
                    63,
                    1829,
                    866,
                    119,
                    44,
                    131,
                    660
                ],
                [
                    149,
                    19,
                    590,
                    144,
                    244,
                    17,
                    43,
                    234
                ],
                [
                    34,
                    7,
                    173,
                    38,
                    22,
                    44,
                    19,
                    61
                ],
                [
                    147,
                    10,
                    694,
                    141,
                    72,
                    16,
                    185,
                    270
                ],
                [
                    507,
                    105,
                    3472,
                    621,
                    237,
                    62,
                    274,
                    2367
                ]
            ],
            [
                [
                    1493,
                    74,
                    1209,
                    166,
                    124,
                    11,
                    53,
                    163,
                    505
                ],
                [
                    56,
                    63,
                    246,
                    51,
                    26,
                    2,
                    4,
                    18,
                    86
                ],
                [
                    1350,
                    300,
                    14102,
                    2002,
                    629,
                    37,
                    192,
                    751,
                    3631
                ],
                [
                    127,
                    43,
                    1911,
                    948,
                    128,
                    6,
                    33,
                    163,
                    606
                ],
                [
                    126,
                    25,
                    681,
                    116,
                    219,
                    2,
                    20,
                    60,
                    199
                ],
                [
                    9,
                    2,
                    31,
                    8,
                    2,
                    13,
                    0,
                    1,
                    7
                ],
                [
                    27,
                    8,
                    163,
                    46,
                    16,
                    1,
                    49,
                    14,
                    60
                ],
                [
                    161,
                    22,
                    685,
                    141,
                    44,
                    3,
                    20,
                    157,
                    263
                ],
                [
                    495,
                    103,
                    3483,
                    695,
                    230,
                    10,
                    67,
                    258,
                    2379
                ]
            ]
        ]
    },
    "RandomForest": {
        "filter_sizes": [
            12000,
            8000,
            6000,
            4500,
            3500,
            1500,
            1000,
            300
        ],
        "training_time_seconds": [
            30.991974115371704,
            45.685502767562866,
            31.665637254714966,
            32.973036766052246,
            33.951300859451294,
            45.93079209327698,
            35.66504740715027,
            35.33432221412659
        ],
        "num_classes": [
            4,
            4,
            6,
            6,
            6,
            8,
            8,
            9
        ],
        "test_f1_macro": [
            0.3928771786061297,
            0.3928771786061297,
            0.2964247061925424,
            0.2964247061925424,
            0.2964247061925424,
            0.2507686386911979,
            0.2507686386911979,
            0.2512718884920807
        ],
        "test_f1_micro": [
            0.6547033887285116,
            0.6547033887285116,
            0.6095378588184083,
            0.6095378588184083,
            0.6095378588184083,
            0.5979084535303699,
            0.5979084535303699,
            0.595922696205515
        ],
        "test_f1_weighted": [
            0.56447513161003,
            0.56447513161003,
            0.5124554058400275,
            0.5124554058400275,
            0.5124554058400275,
            0.4982548389201753,
            0.4982548389201753,
            0.4959428801947849
        ],
        "cv_class_weights": [
            0.8173960609801901,
            0.8173960609801901,
            1.0858271066334115,
            1.0858271066334115,
            1.0858271066334115,
            1.3307505951129175,
            1.3307505951129175,
            1.4512154713728063
        ],
        "imbalance_ratio": [
            5.861513944223107,
            5.861513944223107,
            16.548314606741574,
            16.548314606741574,
            16.548314606741574,
            56.32823259372609,
            56.32823259372609,
            337.7201834862385
        ],
        "total_training_samples": [
            123041,
            123041,
            132321,
            132321,
            132321,
            135555,
            135555,
            135776
        ],
        "entropy": [
            0.7897965464636147,
            0.7897965464636147,
            0.7367764591776876,
            0.7367764591776876,
            0.7367764591776876,
            0.6821026203869703,
            0.6821026203869703,
            0.649862088035378
        ],
        "test_precision_macro": [
            0.7599420854585575,
            0.7599420854585575,
            0.7210970652196899,
            0.7210970652196899,
            0.7210970652196899,
            0.7884875708879504,
            0.7884875708879504,
            0.8053585041424594
        ],
        "test_recall_macro": [
            0.37861328846103687,
            0.37861328846103687,
            0.2772988769247675,
            0.2772988769247675,
            0.2772988769247675,
            0.22386538848605034,
            0.22386538848605034,
            0.21585107766324005
        ],
        "classification_reports": [
            {
                "0": {
                    "precision": 0.8310502283105022,
                    "recall": 0.37574193548387097,
                    "f1-score": 0.5175048871512351,
                    "support": 3875.0
                },
                "1": {
                    "precision": 0.6406192718761456,
                    "recall": 0.9846987429562202,
                    "f1-score": 0.7762382327313732,
                    "support": 23070.0
                },
                "2": {
                    "precision": 0.743801652892562,
                    "recall": 0.04660797514241326,
                    "f1-score": 0.08771929824561403,
                    "support": 3862.0
                },
                "3": {
                    "precision": 0.8242971887550201,
                    "recall": 0.10740450026164312,
                    "f1-score": 0.1900462962962963,
                    "support": 7644.0
                },
                "accuracy": 0.6547033887285116,
                "macro avg": {
                    "precision": 0.7599420854585575,
                    "recall": 0.37861328846103687,
                    "f1-score": 0.3928771786061297,
                    "support": 38451.0
                },
                "weighted avg": {
                    "precision": 0.7066889269772002,
                    "recall": 0.6547033887285116,
                    "f1-score": 0.56447513161003,
                    "support": 38451.0
                }
            },
            {
                "0": {
                    "precision": 0.8310502283105022,
                    "recall": 0.37574193548387097,
                    "f1-score": 0.5175048871512351,
                    "support": 3875.0
                },
                "1": {
                    "precision": 0.6406192718761456,
                    "recall": 0.9846987429562202,
                    "f1-score": 0.7762382327313732,
                    "support": 23070.0
                },
                "2": {
                    "precision": 0.743801652892562,
                    "recall": 0.04660797514241326,
                    "f1-score": 0.08771929824561403,
                    "support": 3862.0
                },
                "3": {
                    "precision": 0.8242971887550201,
                    "recall": 0.10740450026164312,
                    "f1-score": 0.1900462962962963,
                    "support": 7644.0
                },
                "accuracy": 0.6547033887285116,
                "macro avg": {
                    "precision": 0.7599420854585575,
                    "recall": 0.37861328846103687,
                    "f1-score": 0.3928771786061297,
                    "support": 38451.0
                },
                "weighted avg": {
                    "precision": 0.7066889269772002,
                    "recall": 0.6547033887285116,
                    "f1-score": 0.56447513161003,
                    "support": 38451.0
                }
            },
            {
                "0": {
                    "precision": 0.770976253298153,
                    "recall": 0.3709063214013709,
                    "f1-score": 0.5008570449091533,
                    "support": 3939.0
                },
                "1": {
                    "precision": 0.5974091476201853,
                    "recall": 0.9796282592608715,
                    "f1-score": 0.7422003825605171,
                    "support": 22973.0
                },
                "2": {
                    "precision": 0.7272727272727273,
                    "recall": 0.053169734151329244,
                    "f1-score": 0.09909480705097666,
                    "support": 3912.0
                },
                "3": {
                    "precision": 0.48138297872340424,
                    "recall": 0.1312545322697607,
                    "f1-score": 0.20626780626780628,
                    "support": 1379.0
                },
                "4": {
                    "precision": 1.0,
                    "recall": 0.02216252518468771,
                    "f1-score": 0.04336399474375821,
                    "support": 1489.0
                },
                "5": {
                    "precision": 0.7495412844036697,
                    "recall": 0.10667188928058494,
                    "f1-score": 0.18676420162304264,
                    "support": 7659.0
                },
                "accuracy": 0.6095378588184083,
                "macro avg": {
                    "precision": 0.7210970652196899,
                    "recall": 0.2772988769247675,
                    "f1-score": 0.2964247061925424,
                    "support": 41351.0
                },
                "weighted avg": {
                    "precision": 0.6650337487368656,
                    "recall": 0.6095378588184083,
                    "f1-score": 0.5124554058400275,
                    "support": 41351.0
                }
            },
            {
                "0": {
                    "precision": 0.770976253298153,
                    "recall": 0.3709063214013709,
                    "f1-score": 0.5008570449091533,
                    "support": 3939.0
                },
                "1": {
                    "precision": 0.5974091476201853,
                    "recall": 0.9796282592608715,
                    "f1-score": 0.7422003825605171,
                    "support": 22973.0
                },
                "2": {
                    "precision": 0.7272727272727273,
                    "recall": 0.053169734151329244,
                    "f1-score": 0.09909480705097666,
                    "support": 3912.0
                },
                "3": {
                    "precision": 0.48138297872340424,
                    "recall": 0.1312545322697607,
                    "f1-score": 0.20626780626780628,
                    "support": 1379.0
                },
                "4": {
                    "precision": 1.0,
                    "recall": 0.02216252518468771,
                    "f1-score": 0.04336399474375821,
                    "support": 1489.0
                },
                "5": {
                    "precision": 0.7495412844036697,
                    "recall": 0.10667188928058494,
                    "f1-score": 0.18676420162304264,
                    "support": 7659.0
                },
                "accuracy": 0.6095378588184083,
                "macro avg": {
                    "precision": 0.7210970652196899,
                    "recall": 0.2772988769247675,
                    "f1-score": 0.2964247061925424,
                    "support": 41351.0
                },
                "weighted avg": {
                    "precision": 0.6650337487368656,
                    "recall": 0.6095378588184083,
                    "f1-score": 0.5124554058400275,
                    "support": 41351.0
                }
            },
            {
                "0": {
                    "precision": 0.770976253298153,
                    "recall": 0.3709063214013709,
                    "f1-score": 0.5008570449091533,
                    "support": 3939.0
                },
                "1": {
                    "precision": 0.5974091476201853,
                    "recall": 0.9796282592608715,
                    "f1-score": 0.7422003825605171,
                    "support": 22973.0
                },
                "2": {
                    "precision": 0.7272727272727273,
                    "recall": 0.053169734151329244,
                    "f1-score": 0.09909480705097666,
                    "support": 3912.0
                },
                "3": {
                    "precision": 0.48138297872340424,
                    "recall": 0.1312545322697607,
                    "f1-score": 0.20626780626780628,
                    "support": 1379.0
                },
                "4": {
                    "precision": 1.0,
                    "recall": 0.02216252518468771,
                    "f1-score": 0.04336399474375821,
                    "support": 1489.0
                },
                "5": {
                    "precision": 0.7495412844036697,
                    "recall": 0.10667188928058494,
                    "f1-score": 0.18676420162304264,
                    "support": 7659.0
                },
                "accuracy": 0.6095378588184083,
                "macro avg": {
                    "precision": 0.7210970652196899,
                    "recall": 0.2772988769247675,
                    "f1-score": 0.2964247061925424,
                    "support": 41351.0
                },
                "weighted avg": {
                    "precision": 0.6650337487368656,
                    "recall": 0.6095378588184083,
                    "f1-score": 0.5124554058400275,
                    "support": 41351.0
                }
            },
            {
                "0": {
                    "precision": 0.7614727854855923,
                    "recall": 0.3674993561679114,
                    "f1-score": 0.4957443112732326,
                    "support": 3883.0
                },
                "1": {
                    "precision": 1.0,
                    "recall": 0.05362776025236593,
                    "f1-score": 0.10179640718562874,
                    "support": 634.0
                },
                "2": {
                    "precision": 0.5852406749786153,
                    "recall": 0.9818229257262132,
                    "f1-score": 0.7333495736906211,
                    "support": 22996.0
                },
                "3": {
                    "precision": 0.7641196013289037,
                    "recall": 0.06005221932114883,
                    "f1-score": 0.11135318324860809,
                    "support": 3830.0
                },
                "4": {
                    "precision": 0.4728682170542636,
                    "recall": 0.12708333333333333,
                    "f1-score": 0.20032840722495895,
                    "support": 1440.0
                },
                "5": {
                    "precision": 1.0,
                    "recall": 0.0728643216080402,
                    "f1-score": 0.1358313817330211,
                    "support": 398.0
                },
                "6": {
                    "precision": 1.0,
                    "recall": 0.021498371335504887,
                    "f1-score": 0.042091836734693876,
                    "support": 1535.0
                },
                "7": {
                    "precision": 0.7241992882562278,
                    "recall": 0.10647482014388489,
                    "f1-score": 0.18565400843881857,
                    "support": 7645.0
                },
                "accuracy": 0.5979084535303699,
                "macro avg": {
                    "precision": 0.7884875708879504,
                    "recall": 0.22386538848605034,
                    "f1-score": 0.2507686386911979,
                    "support": 42361.0
                },
                "weighted avg": {
                    "precision": 0.6639598983077711,
                    "recall": 0.5979084535303699,
                    "f1-score": 0.4982548389201753,
                    "support": 42361.0
                }
            },
            {
                "0": {
                    "precision": 0.7614727854855923,
                    "recall": 0.3674993561679114,
                    "f1-score": 0.4957443112732326,
                    "support": 3883.0
                },
                "1": {
                    "precision": 1.0,
                    "recall": 0.05362776025236593,
                    "f1-score": 0.10179640718562874,
                    "support": 634.0
                },
                "2": {
                    "precision": 0.5852406749786153,
                    "recall": 0.9818229257262132,
                    "f1-score": 0.7333495736906211,
                    "support": 22996.0
                },
                "3": {
                    "precision": 0.7641196013289037,
                    "recall": 0.06005221932114883,
                    "f1-score": 0.11135318324860809,
                    "support": 3830.0
                },
                "4": {
                    "precision": 0.4728682170542636,
                    "recall": 0.12708333333333333,
                    "f1-score": 0.20032840722495895,
                    "support": 1440.0
                },
                "5": {
                    "precision": 1.0,
                    "recall": 0.0728643216080402,
                    "f1-score": 0.1358313817330211,
                    "support": 398.0
                },
                "6": {
                    "precision": 1.0,
                    "recall": 0.021498371335504887,
                    "f1-score": 0.042091836734693876,
                    "support": 1535.0
                },
                "7": {
                    "precision": 0.7241992882562278,
                    "recall": 0.10647482014388489,
                    "f1-score": 0.18565400843881857,
                    "support": 7645.0
                },
                "accuracy": 0.5979084535303699,
                "macro avg": {
                    "precision": 0.7884875708879504,
                    "recall": 0.22386538848605034,
                    "f1-score": 0.2507686386911979,
                    "support": 42361.0
                },
                "weighted avg": {
                    "precision": 0.6639598983077711,
                    "recall": 0.5979084535303699,
                    "f1-score": 0.4982548389201753,
                    "support": 42361.0
                }
            },
            {
                "0": {
                    "precision": 0.748559455212153,
                    "recall": 0.3762506582411796,
                    "f1-score": 0.500788505344314,
                    "support": 3798.0
                },
                "1": {
                    "precision": 1.0,
                    "recall": 0.05253623188405797,
                    "f1-score": 0.09982788296041308,
                    "support": 552.0
                },
                "2": {
                    "precision": 0.5840611636646366,
                    "recall": 0.9800817604592502,
                    "f1-score": 0.7319378359505676,
                    "support": 22994.0
                },
                "3": {
                    "precision": 0.7585034013605442,
                    "recall": 0.05624211853720051,
                    "f1-score": 0.10471941770368631,
                    "support": 3965.0
                },
                "4": {
                    "precision": 0.4402035623409669,
                    "recall": 0.11947513812154696,
                    "f1-score": 0.18794133623030962,
                    "support": 1448.0
                },
                "5": {
                    "precision": 1.0,
                    "recall": 0.1506849315068493,
                    "f1-score": 0.2619047619047619,
                    "support": 73.0
                },
                "6": {
                    "precision": 1.0,
                    "recall": 0.08072916666666667,
                    "f1-score": 0.1493975903614458,
                    "support": 384.0
                },
                "7": {
                    "precision": 1.0,
                    "recall": 0.020053475935828877,
                    "f1-score": 0.039318479685452164,
                    "support": 1496.0
                },
                "8": {
                    "precision": 0.7168989547038328,
                    "recall": 0.10660621761658032,
                    "f1-score": 0.1856111862877763,
                    "support": 7720.0
                },
                "accuracy": 0.595922696205515,
                "macro avg": {
                    "precision": 0.8053585041424594,
                    "recall": 0.21585107766324005,
                    "f1-score": 0.2512718884920807,
                    "support": 42430.0
                },
                "weighted avg": {
                    "precision": 0.6589034146400725,
                    "recall": 0.595922696205515,
                    "f1-score": 0.4959428801947849,
                    "support": 42430.0
                }
            }
        ],
        "confusion_matrices": [
            [
                [
                    1456,
                    2391,
                    0,
                    28
                ],
                [
                    183,
                    22717,
                    44,
                    126
                ],
                [
                    15,
                    3646,
                    180,
                    21
                ],
                [
                    98,
                    6707,
                    18,
                    821
                ]
            ],
            [
                [
                    1456,
                    2391,
                    0,
                    28
                ],
                [
                    183,
                    22717,
                    44,
                    126
                ],
                [
                    15,
                    3646,
                    180,
                    21
                ],
                [
                    98,
                    6707,
                    18,
                    821
                ]
            ],
            [
                [
                    1461,
                    2411,
                    1,
                    37,
                    0,
                    29
                ],
                [
                    207,
                    22505,
                    47,
                    66,
                    0,
                    148
                ],
                [
                    12,
                    3613,
                    208,
                    53,
                    0,
                    26
                ],
                [
                    37,
                    1115,
                    1,
                    181,
                    0,
                    45
                ],
                [
                    93,
                    1316,
                    9,
                    13,
                    33,
                    25
                ],
                [
                    85,
                    6711,
                    20,
                    26,
                    0,
                    817
                ]
            ],
            [
                [
                    1461,
                    2411,
                    1,
                    37,
                    0,
                    29
                ],
                [
                    207,
                    22505,
                    47,
                    66,
                    0,
                    148
                ],
                [
                    12,
                    3613,
                    208,
                    53,
                    0,
                    26
                ],
                [
                    37,
                    1115,
                    1,
                    181,
                    0,
                    45
                ],
                [
                    93,
                    1316,
                    9,
                    13,
                    33,
                    25
                ],
                [
                    85,
                    6711,
                    20,
                    26,
                    0,
                    817
                ]
            ],
            [
                [
                    1461,
                    2411,
                    1,
                    37,
                    0,
                    29
                ],
                [
                    207,
                    22505,
                    47,
                    66,
                    0,
                    148
                ],
                [
                    12,
                    3613,
                    208,
                    53,
                    0,
                    26
                ],
                [
                    37,
                    1115,
                    1,
                    181,
                    0,
                    45
                ],
                [
                    93,
                    1316,
                    9,
                    13,
                    33,
                    25
                ],
                [
                    85,
                    6711,
                    20,
                    26,
                    0,
                    817
                ]
            ],
            [
                [
                    1427,
                    0,
                    2362,
                    0,
                    48,
                    0,
                    0,
                    46
                ],
                [
                    18,
                    34,
                    579,
                    0,
                    3,
                    0,
                    0,
                    0
                ],
                [
                    189,
                    0,
                    22578,
                    41,
                    56,
                    0,
                    0,
                    132
                ],
                [
                    15,
                    0,
                    3500,
                    230,
                    59,
                    0,
                    0,
                    26
                ],
                [
                    42,
                    0,
                    1142,
                    4,
                    183,
                    0,
                    0,
                    69
                ],
                [
                    16,
                    0,
                    331,
                    0,
                    4,
                    29,
                    0,
                    18
                ],
                [
                    86,
                    0,
                    1384,
                    6,
                    7,
                    0,
                    33,
                    19
                ],
                [
                    81,
                    0,
                    6703,
                    20,
                    27,
                    0,
                    0,
                    814
                ]
            ],
            [
                [
                    1427,
                    0,
                    2362,
                    0,
                    48,
                    0,
                    0,
                    46
                ],
                [
                    18,
                    34,
                    579,
                    0,
                    3,
                    0,
                    0,
                    0
                ],
                [
                    189,
                    0,
                    22578,
                    41,
                    56,
                    0,
                    0,
                    132
                ],
                [
                    15,
                    0,
                    3500,
                    230,
                    59,
                    0,
                    0,
                    26
                ],
                [
                    42,
                    0,
                    1142,
                    4,
                    183,
                    0,
                    0,
                    69
                ],
                [
                    16,
                    0,
                    331,
                    0,
                    4,
                    29,
                    0,
                    18
                ],
                [
                    86,
                    0,
                    1384,
                    6,
                    7,
                    0,
                    33,
                    19
                ],
                [
                    81,
                    0,
                    6703,
                    20,
                    27,
                    0,
                    0,
                    814
                ]
            ],
            [
                [
                    1429,
                    0,
                    2279,
                    0,
                    49,
                    0,
                    0,
                    0,
                    41
                ],
                [
                    12,
                    29,
                    497,
                    0,
                    5,
                    0,
                    0,
                    0,
                    9
                ],
                [
                    201,
                    0,
                    22536,
                    42,
                    57,
                    0,
                    0,
                    0,
                    158
                ],
                [
                    22,
                    0,
                    3635,
                    223,
                    55,
                    0,
                    0,
                    0,
                    30
                ],
                [
                    47,
                    0,
                    1169,
                    1,
                    173,
                    0,
                    0,
                    0,
                    58
                ],
                [
                    1,
                    0,
                    59,
                    0,
                    2,
                    11,
                    0,
                    0,
                    0
                ],
                [
                    13,
                    0,
                    320,
                    2,
                    3,
                    0,
                    31,
                    0,
                    15
                ],
                [
                    88,
                    0,
                    1346,
                    2,
                    16,
                    0,
                    0,
                    30,
                    14
                ],
                [
                    96,
                    0,
                    6744,
                    24,
                    33,
                    0,
                    0,
                    0,
                    823
                ]
            ]
        ]
    },
    "XGBoost": {
        "filter_sizes": [
            12000,
            8000,
            6000,
            4500,
            3500,
            1500,
            1000,
            300
        ],
        "training_time_seconds": [
            538.0235850811005,
            568.4844045639038,
            742.9555418491364,
            706.7494940757751,
            719.8250875473022,
            916.2976105213165,
            937.8513469696045,
            997.5095431804657
        ],
        "num_classes": [
            4,
            4,
            6,
            6,
            6,
            8,
            8,
            9
        ],
        "test_f1_macro": [
            0.5177918571059776,
            0.5177918571059776,
            0.40129936415328277,
            0.40129936415328277,
            0.40129936415328277,
            0.3424067634802617,
            0.3424067634802617,
            0.33542244259615095
        ],
        "test_f1_micro": [
            0.6874723674286755,
            0.6874723674286755,
            0.6445793330270126,
            0.6445793330270126,
            0.6445793330270126,
            0.6306980477325842,
            0.6306980477325842,
            0.6284468536412915
        ],
        "test_f1_weighted": [
            0.6439165461456533,
            0.6439165461456533,
            0.5918670292158642,
            0.5918670292158642,
            0.5918670292158642,
            0.574485176737396,
            0.574485176737396,
            0.5714358117547857
        ],
        "cv_class_weights": [
            0.8173960609801901,
            0.8173960609801901,
            1.0858271066334115,
            1.0858271066334115,
            1.0858271066334115,
            1.3307505951129175,
            1.3307505951129175,
            1.4512154713728063
        ],
        "imbalance_ratio": [
            5.861513944223107,
            5.861513944223107,
            16.548314606741574,
            16.548314606741574,
            16.548314606741574,
            56.32823259372609,
            56.32823259372609,
            337.7201834862385
        ],
        "total_training_samples": [
            123041,
            123041,
            132321,
            132321,
            132321,
            135555,
            135555,
            135776
        ],
        "entropy": [
            0.7897965464636147,
            0.7897965464636147,
            0.7367764591776876,
            0.7367764591776876,
            0.7367764591776876,
            0.6821026203869703,
            0.6821026203869703,
            0.649862088035378
        ],
        "test_precision_macro": [
            0.6862487831817112,
            0.6862487831817112,
            0.6519644086433426,
            0.6519644086433426,
            0.6519644086433426,
            0.7279523046531331,
            0.7279523046531331,
            0.7565670947226959
        ],
        "test_recall_macro": [
            0.47227840225176765,
            0.47227840225176765,
            0.3559563131996823,
            0.3559563131996823,
            0.3559563131996823,
            0.2904585115093908,
            0.2904585115093908,
            0.2762924720340137
        ],
        "classification_reports": [
            {
                "0": {
                    "precision": 0.7802709568162574,
                    "recall": 0.47561290322580646,
                    "f1-score": 0.5909892576559244,
                    "support": 3875.0
                },
                "1": {
                    "precision": 0.6855333966445077,
                    "recall": 0.9387082791504118,
                    "f1-score": 0.7923893157702159,
                    "support": 23070.0
                },
                "2": {
                    "precision": 0.6133217993079585,
                    "recall": 0.1835836354220611,
                    "f1-score": 0.2825827022718214,
                    "support": 3862.0
                },
                "3": {
                    "precision": 0.6658689799581214,
                    "recall": 0.29120879120879123,
                    "f1-score": 0.40520615272594884,
                    "support": 7644.0
                },
                "accuracy": 0.6874723674286755,
                "macro avg": {
                    "precision": 0.6862487831817112,
                    "recall": 0.47227840225176765,
                    "f1-score": 0.5177918571059776,
                    "support": 38451.0
                },
                "weighted avg": {
                    "precision": 0.6839186676543916,
                    "recall": 0.6874723674286755,
                    "f1-score": 0.6439165461456533,
                    "support": 38451.0
                }
            },
            {
                "0": {
                    "precision": 0.7802709568162574,
                    "recall": 0.47561290322580646,
                    "f1-score": 0.5909892576559244,
                    "support": 3875.0
                },
                "1": {
                    "precision": 0.6855333966445077,
                    "recall": 0.9387082791504118,
                    "f1-score": 0.7923893157702159,
                    "support": 23070.0
                },
                "2": {
                    "precision": 0.6133217993079585,
                    "recall": 0.1835836354220611,
                    "f1-score": 0.2825827022718214,
                    "support": 3862.0
                },
                "3": {
                    "precision": 0.6658689799581214,
                    "recall": 0.29120879120879123,
                    "f1-score": 0.40520615272594884,
                    "support": 7644.0
                },
                "accuracy": 0.6874723674286755,
                "macro avg": {
                    "precision": 0.6862487831817112,
                    "recall": 0.47227840225176765,
                    "f1-score": 0.5177918571059776,
                    "support": 38451.0
                },
                "weighted avg": {
                    "precision": 0.6839186676543916,
                    "recall": 0.6874723674286755,
                    "f1-score": 0.6439165461456533,
                    "support": 38451.0
                }
            },
            {
                "0": {
                    "precision": 0.7182170542635659,
                    "recall": 0.47042396547347043,
                    "f1-score": 0.5684921000153398,
                    "support": 3939.0
                },
                "1": {
                    "precision": 0.6423658872077029,
                    "recall": 0.9350977234144431,
                    "f1-score": 0.7615705042985021,
                    "support": 22973.0
                },
                "2": {
                    "precision": 0.5970149253731343,
                    "recall": 0.19427402862985685,
                    "f1-score": 0.29315332690453233,
                    "support": 3912.0
                },
                "3": {
                    "precision": 0.536734693877551,
                    "recall": 0.19071791153009426,
                    "f1-score": 0.2814339218833601,
                    "support": 1379.0
                },
                "4": {
                    "precision": 0.7777777777777778,
                    "recall": 0.056413700470114174,
                    "f1-score": 0.10519724483406387,
                    "support": 1489.0
                },
                "5": {
                    "precision": 0.6396761133603239,
                    "recall": 0.2888105496801149,
                    "f1-score": 0.3979490869838985,
                    "support": 7659.0
                },
                "accuracy": 0.6445793330270126,
                "macro avg": {
                    "precision": 0.6519644086433426,
                    "recall": 0.3559563131996823,
                    "f1-score": 0.40129936415328277,
                    "support": 41351.0
                },
                "weighted avg": {
                    "precision": 0.6461560421228367,
                    "recall": 0.6445793330270126,
                    "f1-score": 0.5918670292158642,
                    "support": 41351.0
                }
            },
            {
                "0": {
                    "precision": 0.7182170542635659,
                    "recall": 0.47042396547347043,
                    "f1-score": 0.5684921000153398,
                    "support": 3939.0
                },
                "1": {
                    "precision": 0.6423658872077029,
                    "recall": 0.9350977234144431,
                    "f1-score": 0.7615705042985021,
                    "support": 22973.0
                },
                "2": {
                    "precision": 0.5970149253731343,
                    "recall": 0.19427402862985685,
                    "f1-score": 0.29315332690453233,
                    "support": 3912.0
                },
                "3": {
                    "precision": 0.536734693877551,
                    "recall": 0.19071791153009426,
                    "f1-score": 0.2814339218833601,
                    "support": 1379.0
                },
                "4": {
                    "precision": 0.7777777777777778,
                    "recall": 0.056413700470114174,
                    "f1-score": 0.10519724483406387,
                    "support": 1489.0
                },
                "5": {
                    "precision": 0.6396761133603239,
                    "recall": 0.2888105496801149,
                    "f1-score": 0.3979490869838985,
                    "support": 7659.0
                },
                "accuracy": 0.6445793330270126,
                "macro avg": {
                    "precision": 0.6519644086433426,
                    "recall": 0.3559563131996823,
                    "f1-score": 0.40129936415328277,
                    "support": 41351.0
                },
                "weighted avg": {
                    "precision": 0.6461560421228367,
                    "recall": 0.6445793330270126,
                    "f1-score": 0.5918670292158642,
                    "support": 41351.0
                }
            },
            {
                "0": {
                    "precision": 0.7182170542635659,
                    "recall": 0.47042396547347043,
                    "f1-score": 0.5684921000153398,
                    "support": 3939.0
                },
                "1": {
                    "precision": 0.6423658872077029,
                    "recall": 0.9350977234144431,
                    "f1-score": 0.7615705042985021,
                    "support": 22973.0
                },
                "2": {
                    "precision": 0.5970149253731343,
                    "recall": 0.19427402862985685,
                    "f1-score": 0.29315332690453233,
                    "support": 3912.0
                },
                "3": {
                    "precision": 0.536734693877551,
                    "recall": 0.19071791153009426,
                    "f1-score": 0.2814339218833601,
                    "support": 1379.0
                },
                "4": {
                    "precision": 0.7777777777777778,
                    "recall": 0.056413700470114174,
                    "f1-score": 0.10519724483406387,
                    "support": 1489.0
                },
                "5": {
                    "precision": 0.6396761133603239,
                    "recall": 0.2888105496801149,
                    "f1-score": 0.3979490869838985,
                    "support": 7659.0
                },
                "accuracy": 0.6445793330270126,
                "macro avg": {
                    "precision": 0.6519644086433426,
                    "recall": 0.3559563131996823,
                    "f1-score": 0.40129936415328277,
                    "support": 41351.0
                },
                "weighted avg": {
                    "precision": 0.6461560421228367,
                    "recall": 0.6445793330270126,
                    "f1-score": 0.5918670292158642,
                    "support": 41351.0
                }
            },
            {
                "0": {
                    "precision": 0.6956014013234721,
                    "recall": 0.4602111769250579,
                    "f1-score": 0.5539367637941723,
                    "support": 3883.0
                },
                "1": {
                    "precision": 0.9344262295081968,
                    "recall": 0.08990536277602523,
                    "f1-score": 0.16402877697841728,
                    "support": 634.0
                },
                "2": {
                    "precision": 0.6292720037453183,
                    "recall": 0.9352061228039659,
                    "f1-score": 0.7523263135800742,
                    "support": 22996.0
                },
                "3": {
                    "precision": 0.5596676737160121,
                    "recall": 0.19347258485639687,
                    "f1-score": 0.28754365541327126,
                    "support": 3830.0
                },
                "4": {
                    "precision": 0.5544147843942505,
                    "recall": 0.1875,
                    "f1-score": 0.2802283341982356,
                    "support": 1440.0
                },
                "5": {
                    "precision": 1.0,
                    "recall": 0.10301507537688442,
                    "f1-score": 0.1867881548974943,
                    "support": 398.0
                },
                "6": {
                    "precision": 0.8319327731092437,
                    "recall": 0.06449511400651466,
                    "f1-score": 0.11970979443772672,
                    "support": 1535.0
                },
                "7": {
                    "precision": 0.6183035714285714,
                    "recall": 0.2898626553302812,
                    "f1-score": 0.3946923145427019,
                    "support": 7645.0
                },
                "accuracy": 0.6306980477325842,
                "macro avg": {
                    "precision": 0.7279523046531331,
                    "recall": 0.2904585115093908,
                    "f1-score": 0.3424067634802617,
                    "support": 42361.0
                },
                "weighted avg": {
                    "precision": 0.6399286503890075,
                    "recall": 0.6306980477325842,
                    "f1-score": 0.574485176737396,
                    "support": 42361.0
                }
            },
            {
                "0": {
                    "precision": 0.6956014013234721,
                    "recall": 0.4602111769250579,
                    "f1-score": 0.5539367637941723,
                    "support": 3883.0
                },
                "1": {
                    "precision": 0.9344262295081968,
                    "recall": 0.08990536277602523,
                    "f1-score": 0.16402877697841728,
                    "support": 634.0
                },
                "2": {
                    "precision": 0.6292720037453183,
                    "recall": 0.9352061228039659,
                    "f1-score": 0.7523263135800742,
                    "support": 22996.0
                },
                "3": {
                    "precision": 0.5596676737160121,
                    "recall": 0.19347258485639687,
                    "f1-score": 0.28754365541327126,
                    "support": 3830.0
                },
                "4": {
                    "precision": 0.5544147843942505,
                    "recall": 0.1875,
                    "f1-score": 0.2802283341982356,
                    "support": 1440.0
                },
                "5": {
                    "precision": 1.0,
                    "recall": 0.10301507537688442,
                    "f1-score": 0.1867881548974943,
                    "support": 398.0
                },
                "6": {
                    "precision": 0.8319327731092437,
                    "recall": 0.06449511400651466,
                    "f1-score": 0.11970979443772672,
                    "support": 1535.0
                },
                "7": {
                    "precision": 0.6183035714285714,
                    "recall": 0.2898626553302812,
                    "f1-score": 0.3946923145427019,
                    "support": 7645.0
                },
                "accuracy": 0.6306980477325842,
                "macro avg": {
                    "precision": 0.7279523046531331,
                    "recall": 0.2904585115093908,
                    "f1-score": 0.3424067634802617,
                    "support": 42361.0
                },
                "weighted avg": {
                    "precision": 0.6399286503890075,
                    "recall": 0.6306980477325842,
                    "f1-score": 0.574485176737396,
                    "support": 42361.0
                }
            },
            {
                "0": {
                    "precision": 0.7032409215150331,
                    "recall": 0.4741969457609268,
                    "f1-score": 0.5664412643497405,
                    "support": 3798.0
                },
                "1": {
                    "precision": 1.0,
                    "recall": 0.09057971014492754,
                    "f1-score": 0.16611295681063123,
                    "support": 552.0
                },
                "2": {
                    "precision": 0.6256556708241053,
                    "recall": 0.9337218404801253,
                    "f1-score": 0.7492584191240621,
                    "support": 22994.0
                },
                "3": {
                    "precision": 0.590625,
                    "recall": 0.19066834804539723,
                    "f1-score": 0.2882745471877979,
                    "support": 3965.0
                },
                "4": {
                    "precision": 0.5289079229122056,
                    "recall": 0.17058011049723756,
                    "f1-score": 0.2579634464751958,
                    "support": 1448.0
                },
                "5": {
                    "precision": 1.0,
                    "recall": 0.1643835616438356,
                    "f1-score": 0.2823529411764706,
                    "support": 73.0
                },
                "6": {
                    "precision": 0.96,
                    "recall": 0.125,
                    "f1-score": 0.22119815668202766,
                    "support": 384.0
                },
                "7": {
                    "precision": 0.7878787878787878,
                    "recall": 0.05213903743315508,
                    "f1-score": 0.09780564263322884,
                    "support": 1496.0
                },
                "8": {
                    "precision": 0.6127955493741307,
                    "recall": 0.28536269430051814,
                    "f1-score": 0.38939460892620414,
                    "support": 7720.0
                },
                "accuracy": 0.6284468536412915,
                "macro avg": {
                    "precision": 0.7565670947226959,
                    "recall": 0.2762924720340137,
                    "f1-score": 0.33542244259615095,
                    "support": 42430.0
                },
                "weighted avg": {
                    "precision": 0.6379451006376479,
                    "recall": 0.6284468536412915,
                    "f1-score": 0.5714358117547857,
                    "support": 42430.0
                }
            }
        ],
        "confusion_matrices": [
            [
                [
                    1843,
                    1871,
                    11,
                    150
                ],
                [
                    318,
                    21656,
                    313,
                    783
                ],
                [
                    31,
                    2938,
                    709,
                    184
                ],
                [
                    170,
                    5125,
                    123,
                    2226
                ]
            ],
            [
                [
                    1843,
                    1871,
                    11,
                    150
                ],
                [
                    318,
                    21656,
                    313,
                    783
                ],
                [
                    31,
                    2938,
                    709,
                    184
                ],
                [
                    170,
                    5125,
                    123,
                    2226
                ]
            ],
            [
                [
                    1853,
                    1884,
                    4,
                    47,
                    5,
                    146
                ],
                [
                    362,
                    21482,
                    297,
                    82,
                    7,
                    743
                ],
                [
                    23,
                    2915,
                    760,
                    51,
                    2,
                    161
                ],
                [
                    58,
                    937,
                    28,
                    263,
                    4,
                    89
                ],
                [
                    133,
                    1106,
                    44,
                    15,
                    84,
                    107
                ],
                [
                    151,
                    5118,
                    140,
                    32,
                    6,
                    2212
                ]
            ],
            [
                [
                    1853,
                    1884,
                    4,
                    47,
                    5,
                    146
                ],
                [
                    362,
                    21482,
                    297,
                    82,
                    7,
                    743
                ],
                [
                    23,
                    2915,
                    760,
                    51,
                    2,
                    161
                ],
                [
                    58,
                    937,
                    28,
                    263,
                    4,
                    89
                ],
                [
                    133,
                    1106,
                    44,
                    15,
                    84,
                    107
                ],
                [
                    151,
                    5118,
                    140,
                    32,
                    6,
                    2212
                ]
            ],
            [
                [
                    1853,
                    1884,
                    4,
                    47,
                    5,
                    146
                ],
                [
                    362,
                    21482,
                    297,
                    82,
                    7,
                    743
                ],
                [
                    23,
                    2915,
                    760,
                    51,
                    2,
                    161
                ],
                [
                    58,
                    937,
                    28,
                    263,
                    4,
                    89
                ],
                [
                    133,
                    1106,
                    44,
                    15,
                    84,
                    107
                ],
                [
                    151,
                    5118,
                    140,
                    32,
                    6,
                    2212
                ]
            ],
            [
                [
                    1787,
                    0,
                    1844,
                    7,
                    55,
                    0,
                    4,
                    186
                ],
                [
                    36,
                    57,
                    499,
                    11,
                    4,
                    0,
                    0,
                    27
                ],
                [
                    336,
                    2,
                    21506,
                    362,
                    65,
                    0,
                    4,
                    721
                ],
                [
                    23,
                    1,
                    2831,
                    741,
                    42,
                    0,
                    3,
                    189
                ],
                [
                    69,
                    0,
                    933,
                    33,
                    270,
                    0,
                    3,
                    132
                ],
                [
                    24,
                    0,
                    285,
                    20,
                    7,
                    41,
                    0,
                    21
                ],
                [
                    142,
                    1,
                    1152,
                    40,
                    9,
                    0,
                    99,
                    92
                ],
                [
                    152,
                    0,
                    5126,
                    110,
                    35,
                    0,
                    6,
                    2216
                ]
            ],
            [
                [
                    1787,
                    0,
                    1844,
                    7,
                    55,
                    0,
                    4,
                    186
                ],
                [
                    36,
                    57,
                    499,
                    11,
                    4,
                    0,
                    0,
                    27
                ],
                [
                    336,
                    2,
                    21506,
                    362,
                    65,
                    0,
                    4,
                    721
                ],
                [
                    23,
                    1,
                    2831,
                    741,
                    42,
                    0,
                    3,
                    189
                ],
                [
                    69,
                    0,
                    933,
                    33,
                    270,
                    0,
                    3,
                    132
                ],
                [
                    24,
                    0,
                    285,
                    20,
                    7,
                    41,
                    0,
                    21
                ],
                [
                    142,
                    1,
                    1152,
                    40,
                    9,
                    0,
                    99,
                    92
                ],
                [
                    152,
                    0,
                    5126,
                    110,
                    35,
                    0,
                    6,
                    2216
                ]
            ],
            [
                [
                    1801,
                    0,
                    1763,
                    6,
                    55,
                    0,
                    0,
                    2,
                    171
                ],
                [
                    28,
                    50,
                    425,
                    16,
                    3,
                    0,
                    0,
                    0,
                    30
                ],
                [
                    342,
                    0,
                    21470,
                    318,
                    67,
                    0,
                    2,
                    4,
                    791
                ],
                [
                    30,
                    0,
                    2962,
                    756,
                    35,
                    0,
                    0,
                    4,
                    178
                ],
                [
                    65,
                    0,
                    1003,
                    23,
                    247,
                    0,
                    0,
                    3,
                    107
                ],
                [
                    3,
                    0,
                    56,
                    1,
                    1,
                    12,
                    0,
                    0,
                    0
                ],
                [
                    16,
                    0,
                    278,
                    10,
                    5,
                    0,
                    48,
                    0,
                    27
                ],
                [
                    129,
                    0,
                    1151,
                    34,
                    16,
                    0,
                    0,
                    78,
                    88
                ],
                [
                    147,
                    0,
                    5208,
                    116,
                    38,
                    0,
                    0,
                    8,
                    2203
                ]
            ]
        ]
    }
}